gcreds.py
gcreds-0.3.0.data/scripts/gcreds
gcreds-0.3.0.dist-info/DESCRIPTION.rst
gcreds-0.3.0.dist-info/METADATA
gcreds-0.3.0.dist-info/RECORD
gcreds-0.3.0.dist-info/WHEEL
gcreds-0.3.0.dist-info/metadata.json
gcreds-0.3.0.dist-info/top_level.txt
