Metadata-Version: 2.0
Name: gcreds
Version: 0.3.0
Summary: gcreds - a credential management tool using google cloud
Home-page: http://github.com/tly1980/gcreds
Author: Tom Tang
Author-email: tly1980@gmail.com
License: MIT
Platform: UNKNOWN
Classifier: Development Status :: 4 - Beta
Classifier: Environment :: Plugins
Classifier: Intended Audience :: Developers
Classifier: License :: OSI Approved :: MIT License
Classifier: Operating System :: OS Independent
Classifier: Programming Language :: Python :: 2.7
Classifier: Programming Language :: Python :: 3.4
Classifier: Programming Language :: Python :: 3.5
Classifier: Programming Language :: Python :: 3.6
Requires-Dist: google-api-python-client
Requires-Dist: google-cloud-datastore
Requires-Dist: google-auth-httplib2
